camo.py
setup.py
camo_client.egg-info/PKG-INFO
camo_client.egg-info/SOURCES.txt
camo_client.egg-info/dependency_links.txt
camo_client.egg-info/requires.txt
camo_client.egg-info/top_level.txt