Metadata-Version: 1.0
Name: camo-client
Version: 0.0.1
Summary: A python client for Github's Camo image proxy
Home-page: https://github.com/sionide21/camo-client
Author: Ben Olive
Author-email: sionide21@gmail.com
License: MIT
Platform: all
Classifier: Development Status :: 4 - Beta
Classifier: Intended Audience :: Developers
Classifier: Operating System :: OS Independent
Classifier: License :: OSI Approved :: MIT License
Classifier: Topic :: Software Development :: Libraries :: Python Modules
Classifier: Topic :: Internet :: Proxy Servers
